 {
  "social_links": {
    "label": "Enlaces sociales",
    "name": "social_links",
    "type": "group",
    "occurrence": {
      "min": 0,
      "max": 5,
      "default": 1
    },
    "children": {
      "icon": {
        "label": "Icono",
        "name": "icon",
        "type": "text",
        "default": "📷"
      },
      "url": {
        "label": "URL",
        "name": "url",
        "type": "url",
        "default": "#"
      }
    },
    "default": [
      {"icon": "📷", "url": "#"}
    ]
  }
}